trame/__init__.py
trame/modules/__init__.py
trame/modules/video.py
trame/widgets/__init__.py
trame/widgets/video.py
trame_video/__init__.py
trame_video/module/__init__.py
trame_video/module/vue2.py
trame_video/module/serve/trame-fabric.js
trame_video/module/serve/trame-panzoom.js
trame_video/module/serve/trame-videothing-comp.css
trame_video/module/serve/trame-videothing-comp.js
trame_video/module/serve/trame-videothing.js
trame_video/widgets/__init__.py
trame_video/widgets/video.py
trame_video-0.0.2.dist-info/LICENSE
trame_video-0.0.2.dist-info/METADATA
trame_video-0.0.2.dist-info/WHEEL
trame_video-0.0.2.dist-info/top_level.txt
trame_video-0.0.2.dist-info/RECORD
